cntimenlp/__init__.py
cntimenlp/enums.py
cntimenlp/normalizer.py
cntimenlp/point.py
cntimenlp/result.py
cntimenlp/unit.py
cntimenlp/helpers/LunarSolarConverter.py
cntimenlp/helpers/__init__.py
cntimenlp/helpers/arrow_helper.py
cntimenlp/helpers/int_common.py
cntimenlp/helpers/str_common.py
cntimenlp/resource/__init__.py
cntimenlp/resource/holiday.py
cntimenlp/resource/pattern.py
cntimenlp/tests/__init__.py
cntimenlp/tests/conftest.py
cntimenlp/tests/test_normalizer.py
cntimenlp/tests/test_point.py
cntimenlp/tests/test_utils.py
cntime_nlp-0.1.2.dist-info/METADATA
cntime_nlp-0.1.2.dist-info/WHEEL
cntime_nlp-0.1.2.dist-info/top_level.txt
cntime_nlp-0.1.2.dist-info/RECORD
